dockerscanParser/__init__.py
dockerscanParser-0.1.0.dist-info/DESCRIPTION.rst
dockerscanParser-0.1.0.dist-info/METADATA
dockerscanParser-0.1.0.dist-info/RECORD
dockerscanParser-0.1.0.dist-info/WHEEL
dockerscanParser-0.1.0.dist-info/metadata.json
dockerscanParser-0.1.0.dist-info/top_level.txt
